check_variables.py
sunsoft.py
version.py
azpipvar-0.1.6.dist-info/METADATA
azpipvar-0.1.6.dist-info/WHEEL
azpipvar-0.1.6.dist-info/entry_points.txt
azpipvar-0.1.6.dist-info/top_level.txt
azpipvar-0.1.6.dist-info/RECORD
