Metadata-Version: 2.2
Name: azpipvar
Version: 0.1.6
Summary: A tool to extract and list variables from Azure Pipeline YAML files
Home-page: https://github.com/greatbody/azure-pipeline-variable-list
Author: greatbody
Author-email: sunruicode@gmail.com
Classifier: Programming Language :: Python :: 3
Classifier: Programming Language :: Python :: 3.8
Classifier: Programming Language :: Python :: 3.9
Classifier: Programming Language :: Python :: 3.10
Classifier: Programming Language :: Python :: 3.11
Classifier: License :: OSI Approved :: MIT License
Classifier: Operating System :: OS Independent
Classifier: Development Status :: 4 - Beta
Classifier: Intended Audience :: Developers
Classifier: Topic :: Software Development :: Build Tools
Requires-Python: >=3.8
Requires-Dist: pyyaml>=6.0.1
Requires-Dist: requests>=2.32.3
Requires-Dist: termcolor>=2.3.0
Provides-Extra: test
Requires-Dist: pytest>=7.0.0; extra == "test"
Requires-Dist: pytest-cov>=4.0.0; extra == "test"
Dynamic: author
Dynamic: author-email
Dynamic: classifier
Dynamic: description
Dynamic: description-content-type
Dynamic: home-page
Dynamic: provides-extra
Dynamic: requires-dist
Dynamic: requires-python
Dynamic: summary
